{
  "configs": [
    "article-resources.xml",
    "blog-api.xml",
    "global.xml"
  ],
  "secureProperties": [
    "anypoint.platform.client_id",
    "anypoint.platform.client_secret"
  ],
  "redeploymentEnabled": true,
  "name": "com.mycompany:praddys_blog:1.0.0-SNAPSHOT",
  "minMuleVersion": "4.4.0",
  "requiredProduct": "MULE_EE",
  "classLoaderModelLoaderDescriptor": {
    "id": "mule",
    "attributes": {
      "exportedPackages": [],
      "exportedResources": [
        "application-types.xml",
        "article-resources.xml",
        "blog-api.xml",
        "default.properties",
        "dev.properties",
        "global.xml",
        "local.properties",
        "log4j2.xml",
        "weave/autogenerated/d714a0b5-0ed7-4178-aea0-009cbbfc020b/Input-Attributes.wev",
        "weave/autogenerated/d714a0b5-0ed7-4178-aea0-009cbbfc020b/Input-Payload.wev",
        "weave/autogenerated/d714a0b5-0ed7-4178-aea0-009cbbfc020b/Input-Variables-outboundHeaders.wev"
      ]
    }
  },
  "bundleDescriptorLoader": {
    "id": "mule",
    "attributes": {}
  }
}